app/__init__.py
app/config.py
app/main.py
app/mcp.py
app/mkdocs_builder.py
app/models.py
app/services.py
app/utils0.py
app/mkdocs-template/.nav.yml
app/mkdocs-template/gitignore
app/mkdocs-template/.tliner/gitignore
app/mkdocs-template/.tliner/mkdocs.yml
app/mkdocs-template/.tliner/hooks/__init__.py
app/mkdocs-template/.tliner/hooks/gen_index.py
app/mkdocs-template/.tliner/hooks/nav_titles.py
app/mkdocs-template/.tliner/hooks/timeliner_server.py
app/mkdocs-template/.tliner/hooks/unwatch_mkdocs.py
install/__init__.py
install/report.md
install/save.md
tline-0.1.10.dist-info/METADATA
tline-0.1.10.dist-info/WHEEL
tline-0.1.10.dist-info/entry_points.txt
tline-0.1.10.dist-info/RECORD
