Metadata-Version: 2.4
Name: tline
Version: 0.1.10
Summary: Timeliner 🌟 - AI's diary. Track AI agent work with markdown log
Author-email: "sinai.io" <r@sinai.io>
License: Proprietary
Keywords: ai-agents,fastmcp,logging,markdown,mcp,milestones
Requires-Python: ==3.12.8
Requires-Dist: aiohttp>=3.9.0
Requires-Dist: fastmcp==2.12.2
Requires-Dist: loguru==0.7.3
Requires-Dist: mdx-breakless-lists==1.0.1
Requires-Dist: mdx-truly-sane-lists==1.3
Requires-Dist: mkdocs-awesome-nav==3.2.0
Requires-Dist: mkdocs-gen-files==0.5.0
Requires-Dist: mkdocs-material==9.6.22
Requires-Dist: mkdocs==1.6.1
Requires-Dist: pydantic==2.11.7
Requires-Dist: python-frontmatter==1.1.0
Requires-Dist: typer==0.17.4
Provides-Extra: dev
Requires-Dist: pytest-mock==3.15.0; extra == 'dev'
Requires-Dist: pytest==8.4.2; extra == 'dev'
